[{
      "id":"1698864261",
      "type":"Нежитлове приміщення",
      "page":"",
      "rent":"",
      "rooms":"2",
      "surface":"37",
      "surface_land":"",
      "price":"$25000",
      "price_sqmt":"",
      "floor":"0",
      "floors":"9",
      "parking":"Прибудинкова територія",
      "region":"",
      "location":"м. Трускавець",
      "address":"вул. Івана Мазепи, 34",
      "object":"",
      "coordinates":"49.284445,23.516057",
      "date":"2023-11-01",
      "seller":"Марія Шологін",
      "phone":"380978082141","description":"Вторинне відремонтоване приміщення, частково з меблями, придатне до використання",
      "link":"","images":""}]
