[{
        "url":"https://www.realestate.in.ua/region/city/boryslav/",
        "title":"місто Борислав"
      },{
        "url":"https://www.realestate.in.ua/region/city/boryslav/apartment/",
        "title":"місто Борислав - Квартири"
      },{
        "url":"https://www.realestate.in.ua/region/city/chervonohrad/",
        "title":"місто Червоноград"
      },{
        "url":"https://www.realestate.in.ua/region/city/chervonohrad/apartment/",
        "title":"місто Червоноград - Квартири"
      },{
        "url":"https://www.realestate.in.ua/region/city/drohobych/",
        "title":"місто Дрогобич"
      },{
        "url":"https://www.realestate.in.ua/region/city/drohobych/apartment/",
        "title":"місто Дрогобич - Квартири"
      },{
        "url":"https://www.realestate.in.ua/region/city/drohobych/house/",
        "title":"місто Дрогобич - Будинки"
      },{
        "url":"https://www.realestate.in.ua/region/city/lviv/",
        "title":"місто Львів"
      },{
        "url":"https://www.realestate.in.ua/region/city/lviv/commercial/",
        "title":"місто Львів - Комерційна нерухомість"
      },{
        "url":"https://www.realestate.in.ua/region/city/lviv/apartment/",
        "title":"місто Львів - Квартири"
      },{
        "url":"https://www.realestate.in.ua/region/city/lviv/house/",
        "title":"місто Львів - Будинки"
      },{
        "url":"https://www.realestate.in.ua/region/city/lviv/agency/",
        "title":"місто Львів - Агенції"
      },{
        "url":"https://www.realestate.in.ua/region/city/lviv/developer/",
        "title":"місто Львів - Забудовники"
      },{
        "url":"https://www.realestate.in.ua/region/city/lviv/realtor/",
        "title":"місто Львів - Продавці, агенти і ріелтори"
      },{
        "url":"https://www.realestate.in.ua/region/city/morshyn/",
        "title":"місто Моршин"
      },{
        "url":"https://www.realestate.in.ua/region/city/morshyn/apartment/",
        "title":"місто Моршин - Квартири"
      },{
        "url":"https://www.realestate.in.ua/region/city/novyi-rozdil/",
        "title":"місто Новий Розділ"
      },{
        "url":"https://www.realestate.in.ua/region/city/novyi-rozdil/apartment/",
        "title":"місто Новий Розділ - Квартири"
      },{
        "url":"https://www.realestate.in.ua/region/city/sambir/",
        "title":"місто Самбір"
      },{
        "url":"https://www.realestate.in.ua/region/city/sambir/apartment/",
        "title":"місто Самбір - Квартири"
      },{
        "url":"https://www.realestate.in.ua/region/city/stryi/",
        "title":"місто Стрий"
      },{
        "url":"https://www.realestate.in.ua/region/city/stryi/apartment/",
        "title":"місто Стрий - Квартири"
      },{
        "url":"https://www.realestate.in.ua/region/city/truskavets/",
        "title":"місто Трускавець"
      },{
        "url":"https://www.realestate.in.ua/region/city/truskavets/apartment/",
        "title":"місто Трускавець - Квартири"
      },{
        "url":"https://www.realestate.in.ua/region/city/truskavets/commercial/",
        "title":"місто Трускавець - Комерційна нерухомість"
      },{
        "url":"https://www.realestate.in.ua/region/city/truskavets/house/",
        "title":"місто Трускавець - Будинки"
      },{
        "url":"https://www.realestate.in.ua/district/chervonohradskyy/",
        "title":"Червоноградський район"
      },{
        "url":"https://www.realestate.in.ua/district/drohobychskyy/",
        "title":"Дрогобицький район"
      },{
        "url":"https://www.realestate.in.ua/district/lvivskyy/",
        "title":"Львівський район"
      },{
        "url":"https://www.realestate.in.ua/district/lvivskyy/apartment/",
        "title":"Львівський район - Квартири"
      },{
        "url":"https://www.realestate.in.ua/district/sambirskyy/",
        "title":"Самбірський район"
      },{
        "url":"https://www.realestate.in.ua/district/stryiskyy/",
        "title":"Стрийський район"
      },{
        "url":"https://www.realestate.in.ua/district/yavorivskyy/",
        "title":"Яворівський район"
      },{
        "url":"https://www.realestate.in.ua/district/zolochivskyy/",
        "title":"Золочівський район"
      },{
        "url":"https://www.realestate.in.ua/district/zolochivskyy/apartment/",
        "title":"Золочівський район - Квартири"
      },{
        "url":"https://www.realestate.in.ua/district/town/belz/",
        "title":"місто Белз"
      },{
        "url":"https://www.realestate.in.ua/district/town/bibrka/",
        "title":"місто Бібрка"
      },{
        "url":"https://www.realestate.in.ua/district/town/bibrka/apartment/",
        "title":"місто Бібрка - Квартири"
      },{
        "url":"https://www.realestate.in.ua/district/town/brody/",
        "title":"місто Броди"
      },{
        "url":"https://www.realestate.in.ua/district/town/brody/house/",
        "title":"місто Броди - Будинки"
      },{
        "url":"https://www.realestate.in.ua/district/town/brody/apartment/",
        "title":"місто Броди - Квартири"
      },{
        "url":"https://www.realestate.in.ua/district/town/busk/",
        "title":"місто Буськ"
      },{
        "url":"https://www.realestate.in.ua/district/town/busk/house/",
        "title":"місто Буськ - Будинки"
      },{
        "url":"https://www.realestate.in.ua/district/town/dobromyl/",
        "title":"місто Добромиль"
      },{
        "url":"https://www.realestate.in.ua/district/town/dobromyl/apartment/",
        "title":"місто Добромиль - Квартири"
      },{
        "url":"https://www.realestate.in.ua/district/town/dobromyl/house/",
        "title":"місто Добромиль - Будинки"
      },{
        "url":"https://www.realestate.in.ua/district/town/dubliany/",
        "title":"місто Дубляни"
      },{
        "url":"https://www.realestate.in.ua/district/town/dubliany/apartment/",
        "title":"місто Дубляни - Квартири"
      },{
        "url":"https://www.realestate.in.ua/district/town/hlyniany/",
        "title":"місто Глиняни"
      },{
        "url":"https://www.realestate.in.ua/district/town/horodok/",
        "title":"місто Городок"
      },{
        "url":"https://www.realestate.in.ua/district/town/kamianka-buzka/",
        "title":"місто Кам'янка-Бузька"
      },{
        "url":"https://www.realestate.in.ua/district/town/kamianka-buzka/apartment/",
        "title":"місто Кам'янка-Бузька - Квартири"
      },{
        "url":"https://www.realestate.in.ua/district/town/khodoriv/",
        "title":"місто Ходорів"
      },{
        "url":"https://www.realestate.in.ua/district/town/khodoriv/house/",
        "title":"місто Ходорів - Будинки"
      },{
        "url":"https://www.realestate.in.ua/district/town/khyriv/",
        "title":"місто Хирів"
      },{
        "url":"https://www.realestate.in.ua/district/town/komarno/",
        "title":"місто Комарно"
      },{
        "url":"https://www.realestate.in.ua/district/town/komarno/house/",
        "title":"місто Комарно - Будинки"
      },{
        "url":"https://www.realestate.in.ua/district/town/mostyska/",
        "title":"місто Мостиська"
      },{
        "url":"https://www.realestate.in.ua/district/town/mostyska/apartment/",
        "title":"місто Мостиська - Квартири"
      },{
        "url":"https://www.realestate.in.ua/district/town/mykolaiv/",
        "title":"місто Миколаїв"
      },{
        "url":"https://www.realestate.in.ua/district/town/novoiavorivsk/",
        "title":"місто Новояворівськ"
      },{
        "url":"https://www.realestate.in.ua/district/town/novoiavorivsk/apartment/",
        "title":"місто Новояворівськ - Квартири"
      },{
        "url":"https://www.realestate.in.ua/district/town/novyi-kalyniv/",
        "title":"місто Новий Калинів"
      },{
        "url":"https://www.realestate.in.ua/district/town/peremyshliany/",
        "title":"місто Перемишляни"
      },{
        "url":"https://www.realestate.in.ua/district/town/peremyshliany/house/",
        "title":"місто Перемишляни - Будинки"
      },{
        "url":"https://www.realestate.in.ua/district/town/pustomyty/",
        "title":"місто Пустомити"
      },{
        "url":"https://www.realestate.in.ua/district/town/pustomyty/apartment/",
        "title":"місто Пустомити - Квартири"
      },{
        "url":"https://www.realestate.in.ua/district/town/radekhiv/",
        "title":"місто Радехів"
      },{
        "url":"https://www.realestate.in.ua/district/town/rava-ruska/",
        "title":"місто Рава-Руська"
      },{
        "url":"https://www.realestate.in.ua/district/town/rudky/",
        "title":"місто Рудки"
      },{
        "url":"https://www.realestate.in.ua/district/town/rudky/house/",
        "title":"місто Рудки - Будинки"
      },{
        "url":"https://www.realestate.in.ua/district/town/skole/",
        "title":"місто Сколе"
      },{
        "url":"https://www.realestate.in.ua/district/town/sokal/",
        "title":"місто Сокаль"
      },{
        "url":"https://www.realestate.in.ua/district/town/sokal/apartment/",
        "title":"місто Сокаль - Квартири"
      },{
        "url":"https://www.realestate.in.ua/district/town/sokal/house/",
        "title":"місто Сокаль - Будинки"
      },{
        "url":"https://www.realestate.in.ua/district/town/sosnivka/",
        "title":"місто Соснівка"
      },{
        "url":"https://www.realestate.in.ua/district/town/staryi-sambir/",
        "title":"місто Старий Самбір"
      },{
        "url":"https://www.realestate.in.ua/district/town/stebnyk/",
        "title":"місто Стебник"
      },{
        "url":"https://www.realestate.in.ua/district/town/sudova-vyshnia/",
        "title":"місто Судова Вишня"
      },{
        "url":"https://www.realestate.in.ua/district/town/turka/",
        "title":"місто Турка"
      },{
        "url":"https://www.realestate.in.ua/district/town/uhniv/",
        "title":"місто Угнів"
      },{
        "url":"https://www.realestate.in.ua/district/town/velyki-mosty/",
        "title":"місто Великі Мости"
      },{
        "url":"https://www.realestate.in.ua/district/town/velyki-mosty/apartment/",
        "title":"місто Великі Мости - Квартири"
      },{
        "url":"https://www.realestate.in.ua/district/town/vynnyky/",
        "title":"місто Винники"
      },{
        "url":"https://www.realestate.in.ua/district/town/vynnyky/apartment/",
        "title":"місто Винники - Квартири"
      },{
        "url":"https://www.realestate.in.ua/district/town/yavoriv/",
        "title":"місто Яворів"
      },{
        "url":"https://www.realestate.in.ua/district/town/yavoriv/apartment/",
        "title":"місто Яворів - Квартири"
      },{
        "url":"https://www.realestate.in.ua/district/town/zhovkva/",
        "title":"місто Жовква"
      },{
        "url":"https://www.realestate.in.ua/district/town/zhovkva/apartment/",
        "title":"місто Жовква - Квартири"
      },{
        "url":"https://www.realestate.in.ua/district/town/zhydachiv/",
        "title":"місто Жидачів"
      },{
        "url":"https://www.realestate.in.ua/district/town/zolochiv/",
        "title":"місто Золочів"
      },{
        "url":"https://www.realestate.in.ua/district/town/zolochiv/house/",
        "title":"місто Золочів - Будинки"
      },{
        "url":"https://www.realestate.in.ua/district/town/zolochiv/apartment/",
        "title":"місто Золочів - Квартири"
      },{
    "url":"https://www.realestate.in.ua/region/lvivska/",
    "title":"Львівська область"
  }
]